{"name":"textformats","version":"1.1.0","author":"Giorgio Gonnella","desc":"Easy specification of text formats for structured data","license":"ISC","skipDirs":[],"skipFiles":[],"skipExt":[],"installDirs":[],"installFiles":[],"installExt":["nim"],"requires":[{"name":"nim","str":">= 1.0.2 & <= 1.4.8","ver":{"kind":"verIntersect","verILeft":{"kind":"verEqLater","ver":"1.0.2"},"verIRight":{"kind":"verEqEarlier","ver":"1.4.8"}}},{"name":"cligen","str":"1.5.19","ver":{"kind":"verEq","ver":"1.5.19"}},{"name":"yaml","str":"0.16.0","ver":{"kind":"verEq","ver":"0.16.0"}},{"name":"regex","str":"0.18.0","ver":{"kind":"verEq","ver":"0.18.0"}},{"name":"nimpy","str":"0.2.0","ver":{"kind":"verEq","ver":"0.2.0"}}],"bin":["tf_spec","tf_validate","tf_decode","tf_encode"],"binDir":"cli","srcDir":"src","backend":"c","ref":"refs/tags/v1.1.0"}