{"name":"pykot","url":"https://github.com/jabbalaci/nimpykot","method":"git","tags":[{"name":"pykot","version":"0.1.0","author":"Laszlo Szathmary (Jabba Laci)","desc":"Porting some Python / Kotlin features to Nim","license":"MIT","skipDirs":[],"skipFiles":[],"skipExt":[],"installDirs":[],"installFiles":[],"installExt":[],"requires":[{"name":"nim","str":">= 0.19.0","ver":{"kind":"verEqLater","ver":"0.19.0"}}],"bin":[],"binDir":"","srcDir":"src","backend":"c","ref":"refs/tags/v0.1.0"},{"name":"pykot","version":"0.1.1","author":"Laszlo Szathmary (Jabba Laci)","desc":"Porting some Python / Kotlin features to Nim","license":"MIT","skipDirs":[],"skipFiles":[],"skipExt":[],"installDirs":[],"installFiles":[],"installExt":[],"requires":[{"name":"nim","str":">= 0.19.0","ver":{"kind":"verEqLater","ver":"0.19.0"}}],"bin":[],"binDir":"","srcDir":"src","backend":"c","ref":"refs/tags/v0.1.1"},{"name":"pykot","version":"0.1.2","author":"Laszlo Szathmary (Jabba Laci)","desc":"Porting some Python / Kotlin features to Nim","license":"MIT","skipDirs":[],"skipFiles":[],"skipExt":[],"installDirs":[],"installFiles":[],"installExt":[],"requires":[{"name":"nim","str":">= 0.19.0","ver":{"kind":"verEqLater","ver":"0.19.0"}}],"bin":[],"binDir":"","srcDir":"src","backend":"c","ref":"refs/tags/v0.1.2"},{"name":"pykot","version":"0.1.3","author":"Laszlo Szathmary (Jabba Laci)","desc":"Porting some Python / Kotlin features to Nim","license":"MIT","skipDirs":[],"skipFiles":[],"skipExt":[],"installDirs":[],"installFiles":[],"installExt":[],"requires":[{"name":"nim","str":">= 0.19.0","ver":{"kind":"verEqLater","ver":"0.19.0"}}],"bin":[],"binDir":"","srcDir":"src","backend":"c","ref":"refs/tags/v0.1.3"},{"name":"pykot","version":"0.2.0","author":"Laszlo Szathmary (Jabba Laci)","desc":"Porting some Python / Kotlin features to Nim","license":"MIT","skipDirs":[],"skipFiles":[],"skipExt":[],"installDirs":[],"installFiles":[],"installExt":[],"requires":[{"name":"nim","str":">= 0.19.0","ver":{"kind":"verEqLater","ver":"0.19.0"}}],"bin":[],"binDir":"","srcDir":"src","backend":"c","ref":"refs/tags/v0.2.0"},{"name":"pykot","version":"0.2.1","author":"Laszlo Szathmary (Jabba Laci)","desc":"Porting some Python / Kotlin features to Nim","license":"MIT","skipDirs":[],"skipFiles":[],"skipExt":[],"installDirs":[],"installFiles":[],"installExt":[],"requires":[{"name":"nim","str":">= 0.19.0","ver":{"kind":"verEqLater","ver":"0.19.0"}}],"bin":[],"binDir":"","srcDir":"src","backend":"c","ref":"refs/tags/v0.2.1"}],"description":"Porting some Python / Kotlin features to Nim","license":"MIT","web":"https://github.com/jabbalaci/nimpykot","refs":["refs/heads/master","refs/tags/v0.1.0","refs/tags/v0.1.1","refs/tags/v0.1.2","refs/tags/v0.1.3","refs/tags/v0.2.0","refs/tags/v0.2.1"],"heads":[{"name":"pykot","version":"0.2.1","author":"Laszlo Szathmary (Jabba Laci)","desc":"Porting some Python / Kotlin features to Nim","license":"MIT","skipDirs":[],"skipFiles":[],"skipExt":[],"installDirs":[],"installFiles":[],"installExt":[],"requires":[{"name":"nim","str":">= 0.19.0","ver":{"kind":"verEqLater","ver":"0.19.0"}}],"bin":[],"binDir":"","srcDir":"src","backend":"c","ref":"refs/heads/master"}]}