{"name":"libu2f","url":"https://github.com/FedericoCeratto/nim-libu2f","method":"git","tags":[{"name":"libu2f","version":"0.1.1","author":"Federico Ceratto","desc":"Wrapper for the libu2f server and client","license":"LGPLv3","skipDirs":[],"skipFiles":[],"skipExt":[],"installDirs":[],"installFiles":[],"installExt":[],"requires":[{"name":"nim","str":">= 0.15.0","ver":{"kind":"verEqLater","ver":"0.15.0"}}],"bin":[],"binDir":"","srcDir":"src","backend":"c","ref":"refs/tags/0.1.1"}],"description":"A wrapper for libu2f, a library for FIDO/U2F","license":"LGPLv3","web":"https://github.com/FedericoCeratto/nim-libu2f","refs":["refs/heads/master","refs/tags/0.1.1"],"heads":[{"name":"libu2f","version":"0.1.1","author":"Federico Ceratto","desc":"Wrapper for the libu2f server and client","license":"LGPLv3","skipDirs":[],"skipFiles":[],"skipExt":[],"installDirs":[],"installFiles":[],"installExt":[],"requires":[{"name":"nim","str":">= 0.15.0","ver":{"kind":"verEqLater","ver":"0.15.0"}}],"bin":[],"binDir":"","srcDir":"src","backend":"c","ref":"refs/heads/master"}]}