{"name":"oshostname","url":"https://github.com/jrfondren/nim-oshostname","method":"git","tags":[],"description":"Get the current hostname with gethostname(2)","license":"MIT","web":"https://github.com/jrfondren/nim-oshostname","refs":["refs/heads/master"],"heads":[{"name":"oshostname","version":"0.1.0","author":"Julian Fondren","desc":"Get the current hostname with gethostname(2)","license":"MIT","skipDirs":[],"skipFiles":[],"skipExt":[],"installDirs":[],"installFiles":[],"installExt":[],"requires":[{"name":"nim","str":">= 1.4.0","ver":{"kind":"verEqLater","ver":"1.4.0"}}],"bin":[],"binDir":"","srcDir":"src","backend":"c","ref":"refs/heads/master"}]}