{"name":"cbor","url":"https://git.sr.ht/~ehmry/nim_cbor","method":"git","tags":[{"name":"cbor","version":"0.5.0","author":"Emery Hemingway","desc":"Concise Binary Object Representation decoder and encoder (RFC7049).","license":"MIT","skipDirs":[],"skipFiles":[],"skipExt":[],"installDirs":[],"installFiles":[],"installExt":[],"requires":[{"name":"nim","str":">= 0.18.0","ver":{"kind":"verEqLater","ver":"0.18.0"}}],"bin":[],"binDir":"","srcDir":"src","backend":"c","ref":"refs/tags/0.5.0"},{"name":"cbor","version":"0.1.0","author":"Emery Hemingway","desc":"CBOR decoder (RFC7049).","license":"MIT","skipDirs":[],"skipFiles":[],"skipExt":[],"installDirs":[],"installFiles":[],"installExt":[],"requires":[{"name":"nim","str":">= 0.17.2","ver":{"kind":"verEqLater","ver":"0.17.2"}}],"bin":[],"binDir":"","srcDir":"","backend":"c","ref":"refs/tags/v0.1.0"},{"name":"cbor","version":"0.2.0","author":"Emery Hemingway","desc":"Concise Binary Object Representation decoder and encoder (RFC7049).","license":"MIT","skipDirs":["test"],"skipFiles":[],"skipExt":[],"installDirs":[],"installFiles":[],"installExt":[],"requires":[{"name":"nim","str":">= 0.17.2","ver":{"kind":"verEqLater","ver":"0.17.2"}}],"bin":[],"binDir":"","srcDir":"","backend":"c","ref":"refs/tags/v0.2.0"},{"name":"cbor","version":"0.3.0","author":"Emery Hemingway","desc":"Concise Binary Object Representation decoder and encoder (RFC7049).","license":"MIT","skipDirs":["test"],"skipFiles":[],"skipExt":[],"installDirs":[],"installFiles":[],"installExt":[],"requires":[{"name":"nim","str":">= 0.17.2","ver":{"kind":"verEqLater","ver":"0.17.2"}}],"bin":[],"binDir":"","srcDir":"","backend":"c","ref":"refs/tags/v0.3.0"},{"name":"cbor","version":"0.4.0","author":"Emery Hemingway","desc":"Concise Binary Object Representation decoder and encoder (RFC7049).","license":"MIT","skipDirs":[],"skipFiles":[],"skipExt":[],"installDirs":[],"installFiles":[],"installExt":[],"requires":[{"name":"nim","str":">= 0.17.2","ver":{"kind":"verEqLater","ver":"0.17.2"}}],"bin":[],"binDir":"","srcDir":"src","backend":"c","ref":"refs/tags/v0.4.0"},{"name":"cbor","version":"0.4.1","author":"Emery Hemingway","desc":"Concise Binary Object Representation decoder and encoder (RFC7049).","license":"MIT","skipDirs":[],"skipFiles":[],"skipExt":[],"installDirs":[],"installFiles":[],"installExt":[],"requires":[{"name":"nim","str":">= 0.18.0","ver":{"kind":"verEqLater","ver":"0.18.0"}}],"bin":[],"binDir":"","srcDir":"src","backend":"c","ref":"refs/tags/v0.4.1"},{"name":"cbor","version":"0.5.1","author":"Emery Hemingway","desc":"Concise Binary Object Representation decoder and encoder (RFC7049).","license":"MIT","skipDirs":[],"skipFiles":[],"skipExt":[],"installDirs":[],"installFiles":[],"installExt":[],"requires":[{"name":"nim","str":">= 0.18.0","ver":{"kind":"verEqLater","ver":"0.18.0"}}],"bin":[],"binDir":"","srcDir":"src","backend":"c","ref":"refs/tags/v0.5.1"},{"name":"cbor","version":"0.5.2","author":"Emery Hemingway","desc":"Concise Binary Object Representation decoder and encoder (RFC7049).","license":"MIT","skipDirs":[],"skipFiles":[],"skipExt":[],"installDirs":[],"installFiles":[],"installExt":[],"requires":[{"name":"nim","str":">= 0.18.0","ver":{"kind":"verEqLater","ver":"0.18.0"}}],"bin":[],"binDir":"","srcDir":"src","backend":"c","ref":"refs/tags/v0.5.2"},{"name":"cbor","version":"0.6.0","author":"Emery Hemingway","desc":"Concise Binary Object Representation decoder and encoder (RFC7049).","license":"MIT","skipDirs":[],"skipFiles":[],"skipExt":[],"installDirs":[],"installFiles":[],"installExt":[],"requires":[{"name":"nim","str":">= 0.20.0","ver":{"kind":"verEqLater","ver":"0.20.0"}}],"bin":[],"binDir":"","srcDir":"src","backend":"c","ref":"refs/tags/v0.6.0"},{"name":"cbor","version":"0.6.0","author":"Emery Hemingway","desc":"Concise Binary Object Representation decoder and encoder (RFC7049).","license":"ISC","skipDirs":["bin"],"skipFiles":[],"skipExt":[],"installDirs":[],"installFiles":[],"installExt":["nim"],"requires":[{"name":"nim","str":">= 0.20.0","ver":{"kind":"verEqLater","ver":"0.20.0"}}],"bin":["bin/cbordiag"],"binDir":"","srcDir":"src","backend":"c","ref":"refs/tags/v0.7.0"},{"name":"cbor","version":"0.7.0","author":"Emery Hemingway","desc":"Concise Binary Object Representation decoder and encoder (RFC7049).","license":"ISC","skipDirs":["bin"],"skipFiles":[],"skipExt":[],"installDirs":[],"installFiles":[],"installExt":["nim"],"requires":[{"name":"nim","str":">= 0.20.0","ver":{"kind":"verEqLater","ver":"0.20.0"}},{"name":"bignum","str":"any version","ver":{"kind":"verAny"}}],"bin":["bin/cbordiag"],"binDir":"","srcDir":"src","backend":"c","ref":"refs/tags/v0.8.0"},{"name":"cbor","version":"0.8.1","author":"Emery Hemingway","desc":"Concise Binary Object Representation decoder and encoder (RFC7049).","license":"ISC","skipDirs":["bin"],"skipFiles":[],"skipExt":[],"installDirs":[],"installFiles":[],"installExt":["nim"],"requires":[{"name":"nim","str":">= 0.20.0","ver":{"kind":"verEqLater","ver":"0.20.0"}},{"name":"bigints","str":"any version","ver":{"kind":"verAny"}}],"bin":["bin/cbordiag"],"binDir":"","srcDir":"src","backend":"c","ref":"refs/tags/v0.8.1"}],"description":"Concise Binary Object Representation decoder (RFC7049).","license":"MIT","web":"https://git.sr.ht/~ehmry/nim_cbor","refs":["refs/heads/master","refs/heads/staging","refs/tags/0.5.0","refs/tags/v0.1.0","refs/tags/v0.2.0","refs/tags/v0.3.0","refs/tags/v0.4.0","refs/tags/v0.4.1","refs/tags/v0.5.1","refs/tags/v0.5.2","refs/tags/v0.6.0","refs/tags/v0.7.0","refs/tags/v0.8.0","refs/tags/v0.8.1"],"heads":[{"name":"cbor","version":"0.8.1","author":"Emery Hemingway","desc":"Concise Binary Object Representation decoder and encoder (RFC7049).","license":"ISC","skipDirs":["bin"],"skipFiles":[],"skipExt":[],"installDirs":[],"installFiles":[],"installExt":["nim"],"requires":[{"name":"nim","str":">= 0.20.0","ver":{"kind":"verEqLater","ver":"0.20.0"}},{"name":"bigints","str":"any version","ver":{"kind":"verAny"}}],"bin":["bin/cbordiag"],"binDir":"","srcDir":"src","backend":"c","ref":"refs/heads/master"},{"name":"cbor","version":"0.6.0","author":"Emery Hemingway","desc":"Concise Binary Object Representation decoder and encoder (RFC7049).","license":"ISC","skipDirs":["bin"],"skipFiles":[],"skipExt":[],"installDirs":[],"installFiles":[],"installExt":["nim"],"requires":[{"name":"nim","str":">= 0.20.0","ver":{"kind":"verEqLater","ver":"0.20.0"}}],"bin":["bin/cbordiag"],"binDir":"","srcDir":"src","backend":"c","ref":"refs/heads/staging"}]}