{"name":"bytes2human","url":"https://github.com/juancarlospaco/nim-bytes2human","method":"git","tags":[],"description":"Convert bytes to kilobytes, megabytes, gigabytes, etc.","license":"LGPLv3","web":"https://github.com/juancarlospaco/nim-bytes2human","refs":["refs/heads/master"],"heads":[{"name":"bytes2human","version":"0.2.2","author":"Juan Carlos","desc":"Convert bytes to kilobytes, megabytes, gigabytes, etc.","license":"MIT","skipDirs":[],"skipFiles":[],"skipExt":[],"installDirs":[],"installFiles":[],"installExt":[],"requires":[{"name":"nim","str":">= 1.0.0","ver":{"kind":"verEqLater","ver":"1.0.0"}}],"bin":[],"binDir":"","srcDir":"src","backend":"c","ref":"refs/heads/master"}]}