{"name":"circleci_client","tags":[],"method":"git","license":"LGPLv3","web":"https://github.com/FedericoCeratto/nim-circleci","url":"https://github.com/FedericoCeratto/nim-circleci","description":"CircleCI API client","refs":["refs/heads/master"],"heads":[{"name":"circleci_client","version":"0.1.0","author":"Federico Ceratto","desc":"CircleCI API client","license":"LGPLv3","skipDirs":[],"skipFiles":[],"skipExt":["nim"],"installDirs":[],"installFiles":[],"installExt":[],"requires":[{"name":"nim","str":">= 0.14.2","ver":{"kind":"verEqLater","ver":"0.14.2"}}],"bin":["circleci_client"],"binDir":"","srcDir":"","backend":"c","ref":"refs/heads/master"}]}