{"name":"paratext","url":"https://github.com/paranim/paratext","method":"git","tags":[{"name":"paratext","version":"0.1.0","author":"oakes","desc":"A library for rendering text with paranim","license":"Public Domain","skipDirs":[],"skipFiles":[],"skipExt":[],"installDirs":[],"installFiles":[],"installExt":[],"requires":[{"name":"nim","str":">= 1.0.6","ver":{"kind":"verEqLater","ver":"1.0.6"}},{"name":"paranim","str":">= 0.1.0","ver":{"kind":"verEqLater","ver":"0.1.0"}}],"bin":[],"binDir":"","srcDir":"src","backend":"c","ref":"refs/tags/0.1.0"},{"name":"paratext","version":"0.10.0","author":"oakes","desc":"A library for rendering text with paranim","license":"Public Domain","skipDirs":[],"skipFiles":[],"skipExt":[],"installDirs":[],"installFiles":[],"installExt":[],"requires":[{"name":"nim","str":">= 1.2.6","ver":{"kind":"verEqLater","ver":"1.2.6"}}],"bin":[],"binDir":"","srcDir":"src","backend":"c","ref":"refs/tags/0.10.0"},{"name":"paratext","version":"0.11.0","author":"oakes","desc":"A library for rendering text with paranim","license":"Public Domain","skipDirs":[],"skipFiles":[],"skipExt":[],"installDirs":[],"installFiles":[],"installExt":[],"requires":[{"name":"nim","str":">= 1.2.6","ver":{"kind":"verEqLater","ver":"1.2.6"}}],"bin":[],"binDir":"","srcDir":"src","backend":"c","ref":"refs/tags/0.11.0"},{"name":"paratext","version":"0.12.0","author":"oakes","desc":"A library for rendering text with paranim","license":"Public Domain","skipDirs":[],"skipFiles":[],"skipExt":[],"installDirs":[],"installFiles":[],"installExt":[],"requires":[{"name":"nim","str":">= 1.2.6","ver":{"kind":"verEqLater","ver":"1.2.6"}}],"bin":[],"binDir":"","srcDir":"src","backend":"c","ref":"refs/tags/0.12.0"},{"name":"paratext","version":"0.2.0","author":"oakes","desc":"A library for rendering text with paranim","license":"Public Domain","skipDirs":[],"skipFiles":[],"skipExt":[],"installDirs":[],"installFiles":[],"installExt":[],"requires":[{"name":"nim","str":">= 1.0.6","ver":{"kind":"verEqLater","ver":"1.0.6"}},{"name":"paranim","str":">= 0.1.0","ver":{"kind":"verEqLater","ver":"0.1.0"}}],"bin":[],"binDir":"","srcDir":"src","backend":"c","ref":"refs/tags/0.2.0"},{"name":"paratext","version":"0.3.0","author":"oakes","desc":"A library for rendering text with paranim","license":"Public Domain","skipDirs":[],"skipFiles":[],"skipExt":[],"installDirs":[],"installFiles":[],"installExt":[],"requires":[{"name":"nim","str":">= 1.0.6","ver":{"kind":"verEqLater","ver":"1.0.6"}},{"name":"paranim","str":">= 0.1.0","ver":{"kind":"verEqLater","ver":"0.1.0"}}],"bin":[],"binDir":"","srcDir":"src","backend":"c","ref":"refs/tags/0.3.0"},{"name":"paratext","version":"0.4.0","author":"oakes","desc":"A library for rendering text with paranim","license":"Public Domain","skipDirs":[],"skipFiles":[],"skipExt":[],"installDirs":[],"installFiles":[],"installExt":[],"requires":[{"name":"nim","str":">= 1.0.6","ver":{"kind":"verEqLater","ver":"1.0.6"}},{"name":"paranim","str":">= 0.1.0","ver":{"kind":"verEqLater","ver":"0.1.0"}}],"bin":[],"binDir":"","srcDir":"src","backend":"c","ref":"refs/tags/0.4.0"},{"name":"paratext","version":"0.5.0","author":"oakes","desc":"A library for rendering text with paranim","license":"Public Domain","skipDirs":[],"skipFiles":[],"skipExt":[],"installDirs":[],"installFiles":[],"installExt":[],"requires":[{"name":"nim","str":">= 1.0.6","ver":{"kind":"verEqLater","ver":"1.0.6"}},{"name":"paranim","str":">= 0.4.0","ver":{"kind":"verEqLater","ver":"0.4.0"}}],"bin":[],"binDir":"","srcDir":"src","backend":"c","ref":"refs/tags/0.5.0"},{"name":"paratext","version":"0.6.0","author":"oakes","desc":"A library for rendering text with paranim","license":"Public Domain","skipDirs":[],"skipFiles":[],"skipExt":[],"installDirs":[],"installFiles":[],"installExt":[],"requires":[{"name":"nim","str":">= 1.0.6","ver":{"kind":"verEqLater","ver":"1.0.6"}},{"name":"paranim","str":">= 0.8.0","ver":{"kind":"verEqLater","ver":"0.8.0"}}],"bin":[],"binDir":"","srcDir":"src","backend":"c","ref":"refs/tags/0.6.0"},{"name":"paratext","version":"0.7.0","author":"oakes","desc":"A library for rendering text with paranim","license":"Public Domain","skipDirs":[],"skipFiles":[],"skipExt":[],"installDirs":[],"installFiles":[],"installExt":[],"requires":[{"name":"nim","str":">= 1.0.6","ver":{"kind":"verEqLater","ver":"1.0.6"}},{"name":"paranim","str":">= 0.9.0","ver":{"kind":"verEqLater","ver":"0.9.0"}}],"bin":[],"binDir":"","srcDir":"src","backend":"c","ref":"refs/tags/0.7.0"},{"name":"paratext","version":"0.8.0","author":"oakes","desc":"A library for rendering text with paranim","license":"Public Domain","skipDirs":[],"skipFiles":[],"skipExt":[],"installDirs":[],"installFiles":[],"installExt":[],"requires":[{"name":"nim","str":">= 1.0.6","ver":{"kind":"verEqLater","ver":"1.0.6"}},{"name":"paranim","str":">= 0.9.0","ver":{"kind":"verEqLater","ver":"0.9.0"}}],"bin":[],"binDir":"","srcDir":"src","backend":"c","ref":"refs/tags/0.8.0"},{"name":"paratext","version":"0.9.0","author":"oakes","desc":"A library for rendering text with paranim","license":"Public Domain","skipDirs":[],"skipFiles":[],"skipExt":[],"installDirs":[],"installFiles":[],"installExt":[],"requires":[{"name":"nim","str":">= 1.2.6","ver":{"kind":"verEqLater","ver":"1.2.6"}},{"name":"paranim","str":">= 0.10.0","ver":{"kind":"verEqLater","ver":"0.10.0"}}],"bin":[],"binDir":"","srcDir":"src","backend":"c","ref":"refs/tags/0.9.0"}],"description":"A library for rendering text with paranim","license":"Public Domain","refs":["refs/heads/master","refs/tags/0.1.0","refs/tags/0.10.0","refs/tags/0.11.0","refs/tags/0.12.0","refs/tags/0.2.0","refs/tags/0.3.0","refs/tags/0.4.0","refs/tags/0.5.0","refs/tags/0.6.0","refs/tags/0.7.0","refs/tags/0.8.0","refs/tags/0.9.0"],"heads":[{"name":"paratext","version":"0.12.0","author":"oakes","desc":"A library for rendering text with paranim","license":"Public Domain","skipDirs":[],"skipFiles":[],"skipExt":[],"installDirs":[],"installFiles":[],"installExt":[],"requires":[{"name":"nim","str":">= 1.2.6","ver":{"kind":"verEqLater","ver":"1.2.6"}}],"bin":[],"binDir":"","srcDir":"src","backend":"c","ref":"refs/heads/master"}]}