{"name":"neverwinter","url":"https://github.com/niv/neverwinter.nim","method":"git","tags":[{"name":"neverwinter","version":"1.1.1","author":"Bernhard Stöckner <niv@nwnx.io>","desc":"Neverwinter Nights 1 data accessor library and utilities","license":"MIT","skipDirs":[],"skipFiles":[],"skipExt":[],"installDirs":["neverwinter"],"installFiles":[],"installExt":[],"requires":[{"name":"nim","str":">= 0.18.0","ver":{"kind":"verEqLater","ver":"0.18.0"}}],"bin":[],"binDir":"bin","srcDir":"src","backend":"c","ref":"refs/tags/1.1.1"},{"name":"neverwinter","version":"1.2.0","author":"Bernhard Stöckner <niv@nwnx.io>","desc":"Neverwinter Nights 1 data accessor library and utilities","license":"MIT","skipDirs":[],"skipFiles":[],"skipExt":[],"installDirs":["neverwinter"],"installFiles":[],"installExt":[],"requires":[{"name":"nim","str":">= 0.18.0","ver":{"kind":"verEqLater","ver":"0.18.0"}}],"bin":[],"binDir":"bin/","srcDir":"","backend":"c","ref":"refs/tags/1.2.0"},{"name":"neverwinter","version":"1.2.1","author":"Bernhard Stöckner <niv@nwnx.io>","desc":"Neverwinter Nights 1 data accessor library and utilities","license":"MIT","skipDirs":[],"skipFiles":[],"skipExt":[],"installDirs":["neverwinter"],"installFiles":[],"installExt":[],"requires":[{"name":"nim","str":">= 0.18.0","ver":{"kind":"verEqLater","ver":"0.18.0"}}],"bin":[],"binDir":"bin/","srcDir":"","backend":"c","ref":"refs/tags/1.2.1"},{"name":"neverwinter","version":"1.2.10","author":"Bernhard Stöckner <niv@nwnx.io>","desc":"Neverwinter Nights 1: Enhanced Edition data accessor library and utilities","license":"MIT","skipDirs":[],"skipFiles":[],"skipExt":[],"installDirs":["neverwinter"],"installFiles":[],"installExt":[],"requires":[{"name":"nim","str":">= 1.0.2","ver":{"kind":"verEqLater","ver":"1.0.2"}}],"bin":[],"binDir":"bin/","srcDir":"","backend":"c","ref":"refs/tags/1.2.10"},{"name":"neverwinter","version":"1.2.10","author":"Bernhard Stöckner <niv@nwnx.io>","desc":"Neverwinter Nights 1: Enhanced Edition data accessor library and utilities","license":"MIT","skipDirs":[],"skipFiles":[],"skipExt":[],"installDirs":["neverwinter"],"installFiles":[],"installExt":[],"requires":[{"name":"nim","str":">= 1.0.2","ver":{"kind":"verEqLater","ver":"1.0.2"}}],"bin":[],"binDir":"bin/","srcDir":"","backend":"c","ref":"refs/tags/1.2.10-1.2.0"},{"name":"neverwinter","version":"1.2.2","author":"Bernhard Stöckner <niv@nwnx.io>","desc":"Neverwinter Nights 1: Enhanced Edition data accessor library and utilities","license":"MIT","skipDirs":[],"skipFiles":[],"skipExt":[],"installDirs":["neverwinter"],"installFiles":[],"installExt":[],"requires":[{"name":"nim","str":">= 0.19.4","ver":{"kind":"verEqLater","ver":"0.19.4"}}],"bin":[],"binDir":"bin/","srcDir":"","backend":"c","ref":"refs/tags/1.2.2"},{"name":"neverwinter","version":"1.2.3","author":"Bernhard Stöckner <niv@nwnx.io>","desc":"Neverwinter Nights 1: Enhanced Edition data accessor library and utilities","license":"MIT","skipDirs":[],"skipFiles":[],"skipExt":[],"installDirs":["neverwinter"],"installFiles":[],"installExt":[],"requires":[{"name":"nim","str":">= 0.19.4","ver":{"kind":"verEqLater","ver":"0.19.4"}}],"bin":[],"binDir":"bin/","srcDir":"","backend":"c","ref":"refs/tags/1.2.3"},{"name":"neverwinter","version":"1.2.4","author":"Bernhard Stöckner <niv@nwnx.io>","desc":"Neverwinter Nights 1: Enhanced Edition data accessor library and utilities","license":"MIT","skipDirs":[],"skipFiles":[],"skipExt":[],"installDirs":["neverwinter"],"installFiles":[],"installExt":[],"requires":[{"name":"nim","str":">= 0.20.0","ver":{"kind":"verEqLater","ver":"0.20.0"}}],"bin":[],"binDir":"bin/","srcDir":"","backend":"c","ref":"refs/tags/1.2.4"},{"name":"neverwinter","version":"1.2.5","author":"Bernhard Stöckner <niv@nwnx.io>","desc":"Neverwinter Nights 1: Enhanced Edition data accessor library and utilities","license":"MIT","skipDirs":[],"skipFiles":[],"skipExt":[],"installDirs":["neverwinter"],"installFiles":[],"installExt":[],"requires":[{"name":"nim","str":">= 0.20.0","ver":{"kind":"verEqLater","ver":"0.20.0"}}],"bin":[],"binDir":"bin/","srcDir":"","backend":"c","ref":"refs/tags/1.2.5"},{"name":"neverwinter","version":"1.2.7","author":"Bernhard Stöckner <niv@nwnx.io>","desc":"Neverwinter Nights 1: Enhanced Edition data accessor library and utilities","license":"MIT","skipDirs":[],"skipFiles":[],"skipExt":[],"installDirs":["neverwinter"],"installFiles":[],"installExt":[],"requires":[{"name":"nim","str":">= 0.20.2","ver":{"kind":"verEqLater","ver":"0.20.2"}}],"bin":[],"binDir":"bin/","srcDir":"","backend":"c","ref":"refs/tags/1.2.7"},{"name":"neverwinter","version":"1.2.8","author":"Bernhard Stöckner <niv@nwnx.io>","desc":"Neverwinter Nights 1: Enhanced Edition data accessor library and utilities","license":"MIT","skipDirs":[],"skipFiles":[],"skipExt":[],"installDirs":["neverwinter"],"installFiles":[],"installExt":[],"requires":[{"name":"nim","str":">= 1.0.2","ver":{"kind":"verEqLater","ver":"1.0.2"}}],"bin":[],"binDir":"bin/","srcDir":"","backend":"c","ref":"refs/tags/1.2.8"},{"name":"neverwinter","version":"1.2.9","author":"Bernhard Stöckner <niv@nwnx.io>","desc":"Neverwinter Nights 1: Enhanced Edition data accessor library and utilities","license":"MIT","skipDirs":[],"skipFiles":[],"skipExt":[],"installDirs":["neverwinter"],"installFiles":[],"installExt":[],"requires":[{"name":"nim","str":">= 1.0.2","ver":{"kind":"verEqLater","ver":"1.0.2"}}],"bin":[],"binDir":"bin/","srcDir":"","backend":"c","ref":"refs/tags/1.2.9"},{"name":"neverwinter","version":"1.3.0","author":"Bernhard Stöckner <niv@nwnx.io>","desc":"Neverwinter Nights 1: Enhanced Edition data accessor library and utilities","license":"MIT","skipDirs":[],"skipFiles":[],"skipExt":[],"installDirs":["neverwinter"],"installFiles":[],"installExt":[],"requires":[{"name":"nim","str":">= 1.0.8","ver":{"kind":"verEqLater","ver":"1.0.8"}}],"bin":[],"binDir":"bin/","srcDir":"","backend":"c","ref":"refs/tags/1.3.0"},{"name":"neverwinter","version":"1.3.1","author":"Bernhard Stöckner <niv@nwnx.io>","desc":"Neverwinter Nights 1: Enhanced Edition data accessor library and utilities","license":"MIT","skipDirs":[],"skipFiles":[],"skipExt":[],"installDirs":["neverwinter"],"installFiles":[],"installExt":[],"requires":[{"name":"nim","str":">= 1.0.8","ver":{"kind":"verEqLater","ver":"1.0.8"}}],"bin":[],"binDir":"bin/","srcDir":"","backend":"c","ref":"refs/tags/1.3.1"},{"name":"neverwinter","version":"1.3.2","author":"Bernhard Stöckner <n@e-ix.net>","desc":"Neverwinter Nights 1: Enhanced Edition data accessor library and utilities","license":"MIT","skipDirs":[],"skipFiles":[],"skipExt":[],"installDirs":["neverwinter"],"installFiles":[],"installExt":[],"requires":[{"name":"nim","str":">= 1.0.8","ver":{"kind":"verEqLater","ver":"1.0.8"}}],"bin":[],"binDir":"bin/","srcDir":"","backend":"c","ref":"refs/tags/1.3.2"},{"name":"neverwinter","version":"1.4.1","author":"Bernhard Stöckner <n@e-ix.net>","desc":"Neverwinter Nights 1: Enhanced Edition data accessor library and utilities","license":"MIT","skipDirs":[],"skipFiles":[],"skipExt":[],"installDirs":["neverwinter"],"installFiles":[],"installExt":[],"requires":[{"name":"nim","str":">= 1.0.8","ver":{"kind":"verEqLater","ver":"1.0.8"}}],"bin":[],"binDir":"bin/","srcDir":"","backend":"c","ref":"refs/tags/1.4.1"},{"name":"neverwinter","version":"1.4.2","author":"Bernhard Stöckner <n@e-ix.net>","desc":"Neverwinter Nights 1: Enhanced Edition data accessor library and utilities","license":"MIT","skipDirs":[],"skipFiles":[],"skipExt":[],"installDirs":["neverwinter"],"installFiles":[],"installExt":[],"requires":[{"name":"nim","str":">= 1.0.8","ver":{"kind":"verEqLater","ver":"1.0.8"}}],"bin":[],"binDir":"bin/","srcDir":"","backend":"c","ref":"refs/tags/1.4.2"},{"name":"neverwinter","version":"1.4.3","author":"Bernhard Stöckner <n@e-ix.net>","desc":"Neverwinter Nights 1: Enhanced Edition data accessor library and utilities","license":"MIT","skipDirs":[],"skipFiles":[],"skipExt":[],"installDirs":["neverwinter"],"installFiles":[],"installExt":[],"requires":[{"name":"nim","str":">= 1.4.8","ver":{"kind":"verEqLater","ver":"1.4.8"}},{"name":"docopt","str":">= 0.6.8","ver":{"kind":"verEqLater","ver":"0.6.8"}}],"bin":[],"binDir":"bin/","srcDir":"","backend":"c","ref":"refs/tags/1.4.3"},{"name":"neverwinter","version":"1.4.4","author":"Bernhard Stöckner <n@e-ix.net>","desc":"Neverwinter Nights 1: Enhanced Edition data accessor library and utilities","license":"MIT","skipDirs":[],"skipFiles":[],"skipExt":[],"installDirs":["neverwinter"],"installFiles":[],"installExt":[],"requires":[{"name":"nim","str":">= 1.4.8","ver":{"kind":"verEqLater","ver":"1.4.8"}},{"name":"docopt","str":">= 0.6.8","ver":{"kind":"verEqLater","ver":"0.6.8"}}],"bin":[],"binDir":"bin/","srcDir":"","backend":"c","ref":"refs/tags/1.4.4"},{"name":"neverwinter","version":"1.4.5","author":"Bernhard Stöckner <n@e-ix.net>","desc":"Neverwinter Nights 1: Enhanced Edition data accessor library and utilities","license":"MIT","skipDirs":[],"skipFiles":[],"skipExt":[],"installDirs":["neverwinter"],"installFiles":[],"installExt":[],"requires":[{"name":"nim","str":">= 1.4.8","ver":{"kind":"verEqLater","ver":"1.4.8"}},{"name":"docopt","str":">= 0.6.8","ver":{"kind":"verEqLater","ver":"0.6.8"}}],"bin":[],"binDir":"bin/","srcDir":"","backend":"c","ref":"refs/tags/1.4.5"},{"name":"neverwinter","version":"1.5.0","author":"Bernhard Stöckner <n@e-ix.net>","desc":"Neverwinter Nights 1: Enhanced Edition data accessor library and utilities","license":"MIT","skipDirs":[],"skipFiles":[],"skipExt":[],"installDirs":["neverwinter"],"installFiles":[],"installExt":[],"requires":[{"name":"nim","str":">= 1.6.0","ver":{"kind":"verEqLater","ver":"1.6.0"}},{"name":"docopt","str":">= 0.6.8","ver":{"kind":"verEqLater","ver":"0.6.8"}}],"bin":[],"binDir":"bin/","srcDir":"","backend":"c","ref":"refs/tags/1.5.0"},{"name":"neverwinter","version":"1.5.0","author":"Bernhard Stöckner <n@e-ix.net>","desc":"Neverwinter Nights 1: Enhanced Edition data accessor library and utilities","license":"MIT","skipDirs":[],"skipFiles":[],"skipExt":[],"installDirs":["neverwinter"],"installFiles":[],"installExt":[],"requires":[{"name":"nim","str":">= 1.6.0","ver":{"kind":"verEqLater","ver":"1.6.0"}},{"name":"docopt","str":">= 0.6.8","ver":{"kind":"verEqLater","ver":"0.6.8"}}],"bin":[],"binDir":"bin/","srcDir":"","backend":"c","ref":"refs/tags/1.5.1"},{"name":"neverwinter","version":"1.5.0","author":"Bernhard Stöckner <n@e-ix.net>","desc":"Neverwinter Nights 1: Enhanced Edition data accessor library and utilities","license":"MIT","skipDirs":[],"skipFiles":[],"skipExt":[],"installDirs":["neverwinter"],"installFiles":[],"installExt":[],"requires":[{"name":"nim","str":">= 1.6.0","ver":{"kind":"verEqLater","ver":"1.6.0"}},{"name":"docopt","str":">= 0.6.8","ver":{"kind":"verEqLater","ver":"0.6.8"}}],"bin":[],"binDir":"bin/","srcDir":"","backend":"c","ref":"refs/tags/1.5.2"},{"name":"neverwinter","version":"1.5.3","author":"Bernhard Stöckner <n@e-ix.net>","desc":"Neverwinter Nights 1: Enhanced Edition data accessor library and utilities","license":"MIT","skipDirs":[],"skipFiles":[],"skipExt":[],"installDirs":["neverwinter"],"installFiles":[],"installExt":[],"requires":[{"name":"nim","str":">= 1.6.0","ver":{"kind":"verEqLater","ver":"1.6.0"}},{"name":"docopt","str":">= 0.6.8","ver":{"kind":"verEqLater","ver":"0.6.8"}}],"bin":[],"binDir":"bin/","srcDir":"","backend":"c","ref":"refs/tags/1.5.3"},{"name":"neverwinter","version":"1.5.4","author":"Bernhard Stöckner <n@e-ix.net>","desc":"Neverwinter Nights 1: Enhanced Edition data accessor library and utilities","license":"MIT","skipDirs":[],"skipFiles":[],"skipExt":[],"installDirs":["neverwinter"],"installFiles":[],"installExt":[],"requires":[{"name":"nim","str":">= 1.6.0","ver":{"kind":"verEqLater","ver":"1.6.0"}},{"name":"docopt","str":">= 0.6.8","ver":{"kind":"verEqLater","ver":"0.6.8"}}],"bin":[],"binDir":"bin/","srcDir":"","backend":"c","ref":"refs/tags/1.5.4"},{"name":"neverwinter","version":"1.5.5","author":"Bernhard Stöckner <n@e-ix.net>","desc":"Neverwinter Nights 1: Enhanced Edition data accessor library and utilities","license":"MIT","skipDirs":[],"skipFiles":[],"skipExt":[],"installDirs":["neverwinter"],"installFiles":[],"installExt":[],"requires":[{"name":"nim","str":">= 1.6.4","ver":{"kind":"verEqLater","ver":"1.6.4"}},{"name":"docopt","str":">= 0.6.8","ver":{"kind":"verEqLater","ver":"0.6.8"}}],"bin":[],"binDir":"bin/","srcDir":"","backend":"c","ref":"refs/tags/1.5.5"},{"ref":"refs/tags/v1.0.0","name":"neverwinter","url":"https://github.com/niv/neverwinter.nim","version":"v1_0_0","desc":"Neverwinter Nights 1 data accessor library","license":"MIT"},{"ref":"refs/tags/v1.0.1","name":"neverwinter","url":"https://github.com/niv/neverwinter.nim","version":"v1_0_1","desc":"Neverwinter Nights 1 data accessor library","license":"MIT"},{"ref":"refs/tags/v1.1.0","name":"neverwinter","url":"https://github.com/niv/neverwinter.nim","version":"v1_1_0","desc":"Neverwinter Nights 1 data accessor library","license":"MIT"}],"description":"Neverwinter Nights 1 data accessor library","license":"MIT","web":"https://github.com/niv/neverwinter.nim","refs":["refs/heads/legacy","refs/heads/master","refs/heads/normalize-floats","refs/heads/yaml","refs/heads/zstd-win32","refs/tags/1.1.1","refs/tags/1.2.0","refs/tags/1.2.1","refs/tags/1.2.10","refs/tags/1.2.10-1.2.0","refs/tags/1.2.2","refs/tags/1.2.3","refs/tags/1.2.4","refs/tags/1.2.5","refs/tags/1.2.7","refs/tags/1.2.8","refs/tags/1.2.9","refs/tags/1.3.0","refs/tags/1.3.1","refs/tags/1.3.2","refs/tags/1.4.1","refs/tags/1.4.2","refs/tags/1.4.3","refs/tags/1.4.4","refs/tags/1.4.5","refs/tags/1.5.0","refs/tags/1.5.1","refs/tags/1.5.2","refs/tags/1.5.3","refs/tags/1.5.4","refs/tags/1.5.5","refs/tags/v1.0.0","refs/tags/v1.0.1","refs/tags/v1.1.0"],"heads":[{"name":"neverwinter","version":"1.5.4","author":"Bernhard Stöckner <n@e-ix.net>","desc":"Neverwinter Nights 1: Enhanced Edition data accessor library and utilities","license":"MIT","skipDirs":[],"skipFiles":[],"skipExt":[],"installDirs":["neverwinter"],"installFiles":[],"installExt":[],"requires":[{"name":"nim","str":">= 1.6.0","ver":{"kind":"verEqLater","ver":"1.6.0"}},{"name":"docopt","str":">= 0.6.8","ver":{"kind":"verEqLater","ver":"0.6.8"}}],"bin":[],"binDir":"bin/","srcDir":"","backend":"c","ref":"refs/heads/master"}]}