{"homepage":"https://github.com/squattingmonk/blarg","versions":[{"nimble":{"author":"Michael A. Sinclair","backend":"c","binDir":".","description":"A basic little argument parser","license":"MIT","requires":[{"name":"nim","range":">= 1.6.0"}],"specialVersion":"0.1.1","srcDir":"src"},"source":{"url":"https://github.com/squattingmonk/blarg","rev":"dbc661f9bd1391013fb2de5d3309ea87d6d6375d","date":"2023-01-01T08:32:56-06:00","path":"/nix/store/37jsbf821mdh1c8bg5zfg1fmj3snkkwx-blarg","sha256":"0gz749xhvfgjq2bxlrbqmixn4c1iz32p56xrzz57yx3jpc26hkqs","fetchLFS":false,"fetchSubmodules":true,"deepClone":false,"leaveDotGit":false,"method":"git"},"version":"0.1.1"},{"nimble":{"author":"Michael A. Sinclair","backend":"c","binDir":".","description":"A basic little argument parser","license":"MIT","requires":[{"name":"nim","range":">= 1.6.0"}],"specialVersion":"0.1.0","srcDir":"src"},"source":{"url":"https://github.com/squattingmonk/blarg","rev":"59ebae2ed50a177c0047359f9d49054a26992910","date":"2022-05-12T04:39:27-05:00","path":"/nix/store/nz7z72pqsy403lbi6013arzhcqxifyg2-blarg","sha256":"15c07spmjkinwxg0laab530x8zizm9srsggml55kqrqrv7mdgzj8","fetchLFS":false,"fetchSubmodules":true,"deepClone":false,"leaveDotGit":false,"method":"git"},"version":"0.1.0"}]}