{
  "homepage": "https://github.com/olliNiinivaara/GuildenStern",
  "src": {
    "method": "git",
    "versions": [
      {
        "name": "1.0.0",
        "value": {
          "url": "https://github.com/olliNiinivaara/GuildenStern",
          "rev": "495aff7d1a364474590a67afca9239214179fab0",
          "date": "2021-01-28T10:43:15+02:00",
          "path": "/nix/store/96xwsjhcljkgf5z4fv9cqkf40vinjalk-GuildenStern",
          "sha256": "0q6m48kvsql7s4wxfa7hsmiilj41bxyx5imfdhrbmyh5dcdl8f4k",
          "fetchSubmodules": false,
          "deepClone": false,
          "leaveDotGit": false
        }
      },
      {
        "name": "0.9",
        "value": {
          "url": "https://github.com/olliNiinivaara/GuildenStern",
          "rev": "e19ebed9ff816a10ebf7a85dd8472733227c92be",
          "date": "2020-11-10T15:04:26+02:00",
          "path": "/nix/store/wbwk7zy675342skizj3ppk8snm95w81c-GuildenStern",
          "sha256": "0nwhx3408622drjk589ilfcafkhif712d3hx45328a9g7c3vsxcl",
          "fetchSubmodules": false,
          "deepClone": false,
          "leaveDotGit": false
        }
      },
      {
        "name": "0.8",
        "value": {
          "url": "https://github.com/olliNiinivaara/GuildenStern",
          "rev": "1b56474e235e7602202762405de2dfb6ea53d38a",
          "date": "2020-10-18T17:36:47+03:00",
          "path": "/nix/store/5xnwghbffi7sx4kafixgfqzpz1yp69dz-GuildenStern",
          "sha256": "1m2g04xp8ar4h6ddx7md3630p5skk44dh8zls2sa1qq7n4kxfcwk",
          "fetchSubmodules": false,
          "deepClone": false,
          "leaveDotGit": false
        }
      },
      {
        "name": "0.7",
        "value": {
          "url": "https://github.com/olliNiinivaara/GuildenStern",
          "rev": "0a9325e28ff0cc699ce1242c763e823d2465faa9",
          "date": "2020-06-01T14:48:41+03:00",
          "path": "/nix/store/acvnq48y3xfqi4crfy3c3lkx9110dwg7-GuildenStern",
          "sha256": "11pjhv1rmx8ss67vr8rb3m8psfc4sdlxzqn7px2vq2xnwf8cqhhl",
          "fetchSubmodules": false,
          "deepClone": false,
          "leaveDotGit": false
        }
      }
    ]
  }
}