{
  "homepage": "https://github.com/SolitudeSF/imageman",
  "src": {
    "method": "git",
    "versions": [
      {
        "name": "0.7.6",
        "value": {
          "url": "https://github.com/SolitudeSF/imageman",
          "rev": "3eb6c80ec788df25eb96677777424b63f6053f4c",
          "date": "2020-12-08T20:53:59+02:00",
          "path": "/nix/store/wlhwz6sbrfnxm4fl0bplgg57y54mh2z7-imageman",
          "sha256": "18p89r55jb3v7jyncg8bcrn1kccilsvjwzcigfrwqj4zhagrjhzh",
          "fetchSubmodules": false,
          "deepClone": false,
          "leaveDotGit": false
        }
      },
      {
        "name": "0.7.5",
        "value": {
          "url": "https://github.com/SolitudeSF/imageman",
          "rev": "79156dd881ec687fb3d447d4419e6019cd21038e",
          "date": "2020-11-05T16:21:20+02:00",
          "path": "/nix/store/dxb3y8ixsm8shvn1fnfnsvdhqk987jnf-imageman",
          "sha256": "18aknkcl3dhw9q709308a43adbiqpzdwp70gfqb6zqyf1gvxxji1",
          "fetchSubmodules": false,
          "deepClone": false,
          "leaveDotGit": false
        }
      },
      {
        "name": "0.7.4",
        "value": {
          "url": "https://github.com/SolitudeSF/imageman",
          "rev": "101d547738a29757c1163f3962265e548e90b869",
          "date": "2020-05-13T13:38:39+03:00",
          "path": "/nix/store/frn2m570m2hkb07rjib16g5igm0nkxn3-imageman",
          "sha256": "0n6w4ikc533xmrv9wxvrars1ajc9rvlfv619j88v8bb5d70v0pgs",
          "fetchSubmodules": false,
          "deepClone": false,
          "leaveDotGit": false
        }
      },
      {
        "name": "0.7.3",
        "value": {
          "url": "https://github.com/SolitudeSF/imageman",
          "rev": "d39d08eeb66c8d310d343ad82de992064da05218",
          "date": "2020-05-12T19:55:34+03:00",
          "path": "/nix/store/jd6xg5ppdq5fzl95f6ff10h4bam1jlzg-imageman",
          "sha256": "0qhbv0ykdplf8gv8sjz7p5i5sb4vmxa5qgg2i9xbmmb25189bkg3",
          "fetchSubmodules": false,
          "deepClone": false,
          "leaveDotGit": false
        }
      },
      {
        "name": "0.7.2",
        "value": {
          "url": "https://github.com/SolitudeSF/imageman",
          "rev": "1d05ff41f73bcec9d3b80edaadcf1e8ee32b0236",
          "date": "2020-05-12T19:38:47+03:00",
          "path": "/nix/store/6hdmz4avi050agg5zx66q1wpg7vz3zph-imageman",
          "sha256": "17fjmbdhfbffv0dqc7hbfyz561hv3zsdw9vjvh1m341whp0j51yv",
          "fetchSubmodules": false,
          "deepClone": false,
          "leaveDotGit": false
        }
      },
      {
        "name": "0.7.1",
        "value": {
          "url": "https://github.com/SolitudeSF/imageman",
          "rev": "30f456a35b5be6da76bac31a2df0c2f2549bf15d",
          "date": "2020-04-22T23:42:34+03:00",
          "path": "/nix/store/kzqrmz3ghsq8llf7s6fr0bd5gvdzyrbp-imageman",
          "sha256": "0gwhxknpmlc246dz4hwfn85h75rll3kk3agir1pja33bmda8bri0",
          "fetchSubmodules": false,
          "deepClone": false,
          "leaveDotGit": false
        }
      },
      {
        "name": "0.7.0",
        "value": {
          "url": "https://github.com/SolitudeSF/imageman",
          "rev": "e147d22d7fcea9d3f1212c03112df1edadfa191c",
          "date": "2020-04-22T17:14:22+03:00",
          "path": "/nix/store/hq7nv9qpcq8392j4a3qqr6adpis016f2-imageman",
          "sha256": "12k7x2rdgp4zzhqdcv1ri8skh8asynmf45020wfqpm189vdl1jgd",
          "fetchSubmodules": false,
          "deepClone": false,
          "leaveDotGit": false
        }
      },
      {
        "name": "0.6.5",
        "value": {
          "url": "https://github.com/SolitudeSF/imageman",
          "rev": "9d47aadd385dc0974104e7575a1e942de52350c2",
          "date": "2020-04-04T09:18:17+03:00",
          "path": "/nix/store/jnn00b2997nscanqhyc2rpyjhxrn87zv-imageman",
          "sha256": "0mghn4b76g2h6247pqb3czr97d23jqm7sf549lwbnz6cnk59r6nk",
          "fetchSubmodules": false,
          "deepClone": false,
          "leaveDotGit": false
        }
      },
      {
        "name": "0.6.4",
        "value": {
          "url": "https://github.com/SolitudeSF/imageman",
          "rev": "2766fc22d8ebb921c8b431dcd0bebd29c4e131e5",
          "date": "2020-03-08T19:37:50+02:00",
          "sha256": "1hvymqvjab4il8sd0prs55mk5hryq122f8g66jbc59l2w9jllig8",
          "fetchSubmodules": false
        }
      },
      {
        "name": "0.6.3",
        "value": {
          "url": "https://github.com/SolitudeSF/imageman",
          "rev": "c14b991c931512f581183fc52230bc3d98e18e91",
          "date": "2019-08-03T23:05:15+03:00",
          "sha256": "05d4v8ic9b0j4n546a21cqrb7nxdamcdcnpyv7sgflmgcx2rfxki",
          "fetchSubmodules": false
        }
      },
      {
        "name": "0.6.2",
        "value": {
          "url": "https://github.com/SolitudeSF/imageman",
          "rev": "de8bd15c0a418eef2082904ea83da4d5dd6067c5",
          "date": "2019-08-03T22:22:25+03:00",
          "sha256": "08zvqqicakavb96jljbyagl1lz0nrs1k7fcs9kvsg17ng65xxfz8",
          "fetchSubmodules": false
        }
      },
      {
        "name": "0.6.1",
        "value": {
          "url": "https://github.com/SolitudeSF/imageman",
          "rev": "e7a8ec4a2ff0659a4831d11d34d3db9842460453",
          "date": "2019-07-31T17:36:30+03:00",
          "sha256": "1rv33wd30ns7mdhrv6v2rs7ywj8y74dzv918rhpnq6wi3y2j7alr",
          "fetchSubmodules": false
        }
      },
      {
        "name": "0.6.0",
        "value": {
          "url": "https://github.com/SolitudeSF/imageman",
          "rev": "ea248dc8c634f12b7f8ae15a9fa695e8b69c0b00",
          "date": "2019-07-30T23:32:04+03:00",
          "sha256": "1bcky214j4c38h362rhzrznfi8234vhil5ccqv2drf7i08wj1850",
          "fetchSubmodules": false
        }
      },
      {
        "name": "0.5.1",
        "value": {
          "url": "https://github.com/SolitudeSF/imageman",
          "rev": "243903157d9590dae3b8b65f751e0ffa92ab518f",
          "date": "2019-07-27T15:46:40+03:00",
          "sha256": "1c4bwj4cg4s44c1acsrk17qzip1gcf2sdmzn9y3x6kdyqcgcwsqs",
          "fetchSubmodules": false
        }
      },
      {
        "name": "0.5.0",
        "value": {
          "url": "https://github.com/SolitudeSF/imageman",
          "rev": "dbbf0615f158357bc6df6eff0343eca1e9d6f233",
          "date": "2019-07-14T20:09:15+03:00",
          "sha256": "04k12w7gxfn47yis3jnrlh4irx8i4hxb7dpa5qq0nb8di6wq5gad",
          "fetchSubmodules": false
        }
      },
      {
        "name": "0.4.0",
        "value": {
          "url": "https://github.com/SolitudeSF/imageman",
          "rev": "1e496febcc3f8c15cb91cee35fab84032e997542",
          "date": "2019-06-29T19:17:33+03:00",
          "sha256": "05jb7nddl3frn9fby8b6rz0wk8yd6jdqpbnznqfgafakb9z5732p",
          "fetchSubmodules": false
        }
      },
      {
        "name": "0.3.0",
        "value": {
          "url": "https://github.com/SolitudeSF/imageman",
          "rev": "f078bb8492ee75404b98103dd02c508a4da3412a",
          "date": "2019-06-28T20:10:06+03:00",
          "sha256": "07bb5az4xj6ck53brd0ggwm2rxqkh0z4znjv2aqb2lvfbp14779j",
          "fetchSubmodules": false
        }
      },
      {
        "name": "0.2.2",
        "value": {
          "url": "https://github.com/SolitudeSF/imageman",
          "rev": "04ef8661a984343c350520d7b37bc4e2f9652807",
          "date": "2019-06-21T14:23:16+03:00",
          "sha256": "0fbzly8jmn1gqr89wmfaqmjykl57vmn0i78dwicmiz8vk17jr6gx",
          "fetchSubmodules": false
        }
      },
      {
        "name": "0.2.1",
        "value": {
          "url": "https://github.com/SolitudeSF/imageman",
          "rev": "3069df1cdaf323634a03db3e9ed2eca832b35fcb",
          "date": "2019-06-21T09:40:11+03:00",
          "sha256": "0i86mr4phx84zqypz759hqsb6cxnnfp590bys14vflpmismgw3aa",
          "fetchSubmodules": false
        }
      },
      {
        "name": "0.2.0",
        "value": {
          "url": "https://github.com/SolitudeSF/imageman",
          "rev": "6d4a493b56f6900888fc76f95e50f768ca7aea32",
          "date": "2019-06-14T17:01:57+03:00",
          "sha256": "0ydq18qrsdxcr4104drq8dpfsq45ppr930p7j74z1djcd8wy2k3s",
          "fetchSubmodules": false
        }
      },
      {
        "name": "0.1.0",
        "value": {
          "url": "https://github.com/SolitudeSF/imageman",
          "rev": "b87f866aecef9f018b339bd39f0297077e70db47",
          "date": "2019-04-25T00:47:24+03:00",
          "sha256": "1yv9lqzjn6xkkqa45kadv8q9dsjzakfpz5qlffk89rmq4zan4mf1",
          "fetchSubmodules": false
        }
      }
    ]
  }
}