{
  "meta": {
    "description": "Access bit mapped portions of bytes in binary data as int variables",
    "homepage": "https://github.com/jlp765/mapbits",
    "license": "MIT"
  },
  "src": {
    "method": "git",
    "versions": [
      {
        "name": "1.0",
        "value": {
          "url": "https://github.com/jlp765/mapbits",
          "rev": "e27d7d3cdea6030d80c46e653ec63848833714c1",
          "date": "2016-08-13T08:34:53+10:00",
          "sha256": "10x1xj7ynw5r5qc7hb4qwads4wz0726hnb1dirw264v6g0mnp30v",
          "fetchSubmodules": false
        }
      }
    ]
  }
}