{
  "name": "nimdeps",
  "meta": {
    "description": "Nim library to bundle dependency files into executable",
    "homepage": "https://github.com/genotrance/nimdeps",
    "license": "MIT"
  },
  "src": {
    "method": "git",
    "versions": [
      {
        "name": "HEAD",
        "value": {
          "url": "https://github.com/genotrance/nimdeps",
          "rev": "ecb2a50557b7718830e0253e2435e31d9490cbeb",
          "date": "2018-06-22T13:18:52-05:00",
          "sha256": "0vv6hynnccgprqh1mpwdic1b20gbjfsv07ydh2x160brcyzdw2ak",
          "fetchSubmodules": false
        }
      }
    ]
  }
}