{
  "meta": {
    "description": "Radix tree wrapper for Nim",
    "homepage": "https://github.com/genotrance/nimrax",
    "license": "MIT"
  },
  "src": {
    "method": "git",
    "versions": [
      {
        "name": "0.1.1",
        "value": {
          "url": "https://github.com/genotrance/nimrax",
          "rev": "173032745766bf30e56b1696fc3a2aade2306350",
          "date": "2018-11-03T16:17:26-05:00",
          "sha256": "02mpnwx81sbjqlwl8gw5k5da9bp5dkwqbj8vba75s9lgkvg0pi69",
          "fetchSubmodules": false
        }
      },
      {
        "name": "0.1.0",
        "value": {
          "url": "https://github.com/genotrance/nimrax",
          "rev": "c3963b1b07f0fc43f244d60f992610faca1a5acd",
          "date": "2018-03-11T17:49:55-05:00",
          "sha256": "0vajjhw0jlwr7y8w31njywnxjh899i3hz48cz2c35x5a5wf7x4pc",
          "fetchSubmodules": false
        }
      }
    ]
  }
}