{
  "homepage": "https://git.sr.ht/~ehmry/nim_opusenc",
  "src": {
    "method": "git",
    "versions": [
      {
        "name": "0.2.0",
        "value": {
          "url": "https://git.sr.ht/~ehmry/nim_opusenc",
          "rev": "7f0c91bc710db309332e0229818199a95f3a865d",
          "date": "2020-06-25T17:47:57+05:30",
          "path": "/nix/store/aln19mknqxn4pkhw6rl09q4gzqzy062w-nim_opusenc",
          "sha256": "0fipgms9cc0vsi6j26f2npn2mlvcgkxqgp65fhmg4lh2mv9zyai1",
          "fetchSubmodules": false,
          "deepClone": false,
          "leaveDotGit": false
        }
      },
      {
        "name": "0.1.0",
        "value": {
          "url": "https://git.sr.ht/~ehmry/nim_opusenc",
          "rev": "322671e76cf927bb96fbd2c83d65641268a60d65",
          "date": "2020-06-17T23:30:54+05:30",
          "path": "/nix/store/63rj6gy2r80xjyfc7di4b633zky8krvq-nim_opusenc",
          "sha256": "1s1hsrv1ac1v0ai4adha52ywidnmz8w1cls93rvjw7rf4j5kfmmf",
          "fetchSubmodules": false,
          "deepClone": false,
          "leaveDotGit": false
        }
      }
    ]
  }
}