{
  "meta": {
    "description": "Prepared SQL statement generator. A lightweight ORM.",
    "homepage": "https://github.com/Araq/ormin",
    "license": "MIT"
  },
  "src": {
    "method": "git",
    "versions": [
      {
        "name": "HEAD",
        "value": {
          "url": "https://github.com/Araq/ormin",
          "rev": "9e4ce1f977adfd9e3103fe6ca76174b110697e27",
          "date": "2019-07-19T19:24:01+02:00",
          "sha256": "08qagwxnn9w1asm1k995ns3bvn1my5kb0nf2pz9grwv26248xw34",
          "fetchSubmodules": false
        }
      }
    ]
  }
}