{
  "homepage": "https://github.com/RaimundHuebel/nimpathname",
  "src": {
    "method": "git",
    "versions": [
      {
        "name": "0.1.0",
        "value": {
          "url": "https://github.com/RaimundHuebel/nimpathname",
          "rev": "b919d74c6b82ccf5733172d7aaae449453ae4576",
          "date": "2020-08-24T17:48:28+02:00",
          "path": "/nix/store/m8mmbsxypjl7k0jkk1vqz3p7b9damz45-nimpathname",
          "sha256": "0zz15h562kmzc6jyxh333rca9axhj7mjq23yn0flmgcrciqwvnbh",
          "fetchSubmodules": false,
          "deepClone": false,
          "leaveDotGit": false
        }
      }
    ]
  }
}