{
  "meta": {
    "description": "RSS library",
    "homepage": "https://github.com/achesak/nim-rss",
    "license": "MIT"
  },
  "src": {
    "method": "git",
    "versions": [
      {
        "name": "HEAD",
        "value": {
          "url": "https://github.com/achesak/nim-rss",
          "rev": "c51da8c22dbc67889e4884c77d459cea92b17926",
          "date": "2019-10-06T00:22:03-04:00",
          "sha256": "0kk01hm3kd46rs6siwx0dp3vy7n7iimmb57zl8kfivh9wzfvg0a5",
          "fetchSubmodules": false
        }
      }
    ]
  }
}