{"homepage":"https://github.com/avahe-kellenberger/seq2d","versions":[{"nimble":{"author":"Avahe Kellenberger","backend":"c","binDir":".","description":"A 2D Sequence Implementation","license":"GPL-2.0-only","requires":[{"name":"nim","range":">= 1.6.4"},{"name":"https://github.com/avahe-kellenberger/nimtest","range":"any version"}],"specialVersion":"0.1.0","srcDir":"src"},"source":{"url":"https://github.com/avahe-kellenberger/seq2d","rev":"5662ad567eaf508798b14dd2a063098ef79d52b8","date":"2022-06-29T18:45:23-04:00","path":"/nix/store/rdgmfbcgnsqf954i4k1yznmxpmr37xv0-seq2d","sha256":"06p39svi05pqkpazabfc5134374ri5nxzwp70r36v04rak1gl07j","fetchLFS":false,"fetchSubmodules":true,"deepClone":false,"leaveDotGit":false,"method":"git"},"version":"HEAD"}]}