{"homepage":"https://github.com/PhilippMDoerner/TinyPool","versions":[{"nimble":{"author":"PhilippMDoerner","backend":"c","binDir":".","description":"A minimalistic connection pooling package","license":"MIT","requires":[{"name":"nim","range":">= 1.6.2"}],"specialVersion":"0.1.0","srcDir":"src"},"source":{"url":"https://github.com/PhilippMDoerner/TinyPool","rev":"35629abbc06595a5c0d775b9586bf91d63433a2c","date":"2022-01-27T19:30:03+01:00","path":"/nix/store/1wgjkx6ybm1xnzkk17n0gpm6fvmk9g1b-TinyPool","sha256":"138zc0n4ifcrrnrbjj9n12dfhbq5pzp7c4a5z17xjijnc34wky95","fetchLFS":false,"fetchSubmodules":true,"deepClone":false,"leaveDotGit":false,"method":"git"},"version":"HEAD"},{"nimble":{"author":"PhilippMDoerner","backend":"c","binDir":".","description":"A minimalistic connection pooling package for sqlite","license":"MIT","requires":[{"name":"nim","range":">= 1.6.2"}],"specialVersion":"0.2.1","srcDir":"src"},"source":{"url":"https://github.com/PhilippMDoerner/TinyPool","rev":"608c619addad6e94076f58f4cfe28e6a7aa0992a","date":"2022-01-31T13:12:53+01:00","path":"/nix/store/pgj7yhn7mshsacb6p7x4f7cqz2chapk9-TinyPool","sha256":"0xv6wrq7brbsqnl498mvgdxnig32gv21185gwmdyl8hjalgahwp7","fetchLFS":false,"fetchSubmodules":true,"deepClone":false,"leaveDotGit":false,"method":"git"},"version":"0.2.1"},{"nimble":{"author":"PhilippMDoerner","backend":"c","binDir":".","description":"A minimalistic connection pooling package","license":"MIT","requires":[{"name":"nim","range":">= 1.6.2"}],"specialVersion":"0.1.0","srcDir":"src"},"source":{"url":"https://github.com/PhilippMDoerner/TinyPool","rev":"dcc30222131cdeb589cf1688367ff94a0d37542b","date":"2022-01-31T13:09:59+01:00","path":"/nix/store/jmcndz2llvb0d7lg1b72zifkgvgjfs7v-TinyPool","sha256":"0vm2q79q37qsf3lf8f46i5g96mxzz33i1qb06w5lz9iv8cgyc6r0","fetchLFS":false,"fetchSubmodules":true,"deepClone":false,"leaveDotGit":false,"method":"git"},"version":"0.2.0"}]}