{"homepage":"https://git.sr.ht/~ehmry/nim_tox","versions":[{"nimble":{"author":"Emery Hemingway","backend":"c","binDir":".","description":"C Tox core wrapper","license":"GPL-3.0-or-later","requires":[{"name":"nim","range":">= 1.2.0"}],"specialVersion":"0.4.0","srcDir":"src"},"source":{"url":"https://git.sr.ht/~ehmry/nim_tox","rev":"4a4a4a5bba3865d531317a132a5fad9ee06283e9","date":"2021-01-20T11:06:29+01:00","path":"/nix/store/sr4y6b0qyjw1kli5w8nzl1glialb7r3w-nim_tox","sha256":"0m4akcl40xka0ddhzgjmkprgi8sw3asjxgx4l8i99a26yqs5lf1l","fetchSubmodules":true,"deepClone":false,"leaveDotGit":false,"method":"git"},"version":"0.4.0"},{"nimble":{"author":"Emery Hemingway","backend":"c","binDir":".","description":"C Tox core wrapper","license":"GPL-3.0-or-later","requires":[{"name":"nim","range":">= 1.2.0"}],"specialVersion":"0.3.1","srcDir":"src"},"source":{"url":"https://git.sr.ht/~ehmry/nim_tox","rev":"d5622563fbd550faf3f75402cd85961b48f6df29","date":"2020-06-18T14:46:50+05:30","path":"/nix/store/qcix9ahx25cd570wf203iafcfxbdq1v3-nim_tox","sha256":"14by4ihj0clnb4xn6cvag91b3jj3sp700wpdxyg0rwbbfd268slx","fetchSubmodules":true,"deepClone":false,"leaveDotGit":false,"method":"git"},"version":"0.3.1"},{"nimble":{"author":"Emery Hemingway","backend":"c","binDir":".","description":"C Tox core wrapper","license":"GPL-3.0-or-later","requires":[{"name":"nim","range":">= 1.2.0"}],"specialVersion":"0.3.0","srcDir":"src"},"source":{"url":"https://git.sr.ht/~ehmry/nim_tox","rev":"fbcbdea644c994ab23cb0f5407f50207ec8470f7","date":"2020-06-18T00:20:13+05:30","path":"/nix/store/7al5l170vnrilbsjah3nkiqkb27k757r-nim_tox","sha256":"01ihmcfqyznrgkxm0ad5w23ajrlrbn8agq5cv154azsja841sny8","fetchSubmodules":true,"deepClone":false,"leaveDotGit":false,"method":"git"},"version":"0.3.0"},{"nimble":{"author":"Emery Hemingway","backend":"c","binDir":".","description":"C Tox core wrapper","license":"GPL-3.0-or-later","requires":[{"name":"nim","range":">= 1.0.2"}],"specialVersion":"0.2.0","srcDir":"src"},"source":{"url":"https://git.sr.ht/~ehmry/nim_tox","rev":"fd12809b8133ea8ed68a34f392983e543e18243e","date":"2020-01-23T15:21:55+01:00","path":"/nix/store/njv795c7d3myarm246lgs442yd8c2ry3-nim_tox","sha256":"0d9ckpns5wlnkxzmm6yawxkgmlg7dl5g0qjzz5cmcifvm41sl4r9","fetchSubmodules":true,"deepClone":false,"leaveDotGit":false,"method":"git"},"version":"0.2.1"},{"nimble":{"author":"Emery Hemingway","backend":"c","binDir":".","description":"C Tox core wrapper","license":"GPL-3.0-or-later","requires":[{"name":"nim","range":">= 1.0.2"}],"specialVersion":"0.2.0","srcDir":"src"},"source":{"url":"https://git.sr.ht/~ehmry/nim_tox","rev":"008aff38d733c2c1f89fea378dcb7f42bce6eb08","date":"2019-12-23T17:54:11+00:00","path":"/nix/store/jy7rn0y0cw6piqhia0bpkfxciv185gch-nim_tox","sha256":"0l6bw6cb647yyf95awsgjxc8hgmpkq2pk70455nq5rc3s0myjbv4","fetchSubmodules":true,"deepClone":false,"leaveDotGit":false,"method":"git"},"version":"0.2.0"},{"nimble":{"author":"Emery Hemingway","backend":"c","binDir":".","description":"C Tox core wrapper","license":"GPL-3.0-or-later","requires":[{"name":"nim","range":">= 1.0.2"}],"specialVersion":"0.1.1","srcDir":"src"},"source":{"url":"https://git.sr.ht/~ehmry/nim_tox","rev":"c67b7e6c40125c567e317eb7b15e08e08e992292","date":"2019-12-17T12:36:18+00:00","path":"/nix/store/gd9b2fc1nni1pkm200gv6xqva8sa2h61-nim_tox","sha256":"02lid5vglkaqbvif5x11d7lwzw3cvsa7lpfdgplx653vvv79ciab","fetchSubmodules":true,"deepClone":false,"leaveDotGit":false,"method":"git"},"version":"0.1.1"},{"nimble":{"author":"Emery Hemingway","backend":"c","binDir":".","description":"C Tox core wrapper","license":"GPL-3.0","requires":[{"name":"nim","range":">= 0.19.4"}],"specialVersion":"0.1.0","srcDir":"src"},"source":{"url":"https://git.sr.ht/~ehmry/nim_tox","rev":"e705a3a9b79022e9cf55fab308c90bff96eb0029","date":"2019-06-05T20:47:50+02:00","path":"/nix/store/l4vbrxbvj45rvz1xsqrk3wn5rbbmq30r-nim_tox","sha256":"0yy8whxhb3dvbzmhj3cl733zc8kqbfva0ykmfaccrx93h9gxlg2d","fetchSubmodules":true,"deepClone":false,"leaveDotGit":false,"method":"git"},"version":"0.1.0"}]}