{"homepage":"https://github.com/JohnAD/ur","versions":[{"nimble":{"author":"John Dupuy","backend":"c","binDir":".","description":"Universal Result objects","license":"MIT","requires":[{"name":"nim","range":">= 0.18.0"}],"specialVersion":"0.1.1","srcDir":"src"},"source":{"url":"https://github.com/JohnAD/ur","rev":"d5a3a6fc1e1f0af3ab4c71868b97f0e92c2bdcb4","date":"2018-07-07T20:36:48-05:00","path":"/nix/store/pjba75wypv7qkg0bwh8n39d7xci5zdk5-ur","sha256":"18z91hykmikrx6wza6czz07sryy2lafhpi5xck0vs27qnicq2v0j","fetchSubmodules":true,"deepClone":false,"leaveDotGit":false,"method":"git"},"version":"0.1.1"}]}